gerri/__init__.py
gerri/api_manager/__init__.py
gerri/batch_processing_manager/__init__.py
gerri/blob_manager/__init__.py
gerri/blob_manager/blob_storage_manager.py
gerri/content_filters/__init__.py
gerri/content_filters/content_filter_manager.py
gerri/database_manager/__init__.py
gerri/database_manager/cosmo_db_manager.py
gerri/llm_manager/__init__.py
gerri/llm_manager/hugging_face/__init__.py
gerri/llm_manager/ollama_manager/__init__.py
gerri/llm_manager/ollama_manager/ollama_manager.py
gerri/llm_manager/openai_manager/__init__.py
gerri/llm_manager/openai_manager/azure_openai_manager.py
gerri/llm_manager/openai_manager/openai_manager.py
gerri/rag_manager/__init__.py
gerri/rag_manager/rag_manager.py
gerri/search_manager/__init__.py
gerri/search_manager/azure_search_manager.py
gerri/summary_tag_manager/__init__.py
gerri/utilities/__init__.py
gerri-1.0.0.dist-info/LICENSE
gerri-1.0.0.dist-info/METADATA
gerri-1.0.0.dist-info/WHEEL
gerri-1.0.0.dist-info/top_level.txt
gerri-1.0.0.dist-info/RECORD
