Metadata-Version: 2.1
Name: gerri
Version: 1.0.0
Summary: Giant Eagle Retrieval and Response Interface (Gerri) Library
Home-page: https://github.com/giant-eagle/Gerri_library
Author: Kanav Kahol PhD
Author-email: kanav.kahol@example.com
License: MIT
Platform: UNKNOWN
Classifier: Programming Language :: Python :: 3
Classifier: License :: OSI Approved :: MIT License
Classifier: Operating System :: OS Independent
Classifier: Development Status :: 4 - Beta
Classifier: Intended Audience :: Developers
Classifier: Topic :: Software Development :: Libraries
Requires-Python: >=3.9
License-File: LICENSE
Requires-Dist: annotated-types==0.7.0
Requires-Dist: anyio==4.6.2.post1
Requires-Dist: azure-appconfiguration==1.7.1
Requires-Dist: azure-common==1.1.28
Requires-Dist: azure-core==1.32.0
Requires-Dist: azure-cosmos==4.7.0
Requires-Dist: azure-identity==1.17.1
Requires-Dist: azure-search-documents==11.5.1
Requires-Dist: azure-storage-blob==12.23.1
Requires-Dist: certifi==2024.8.30
Requires-Dist: cffi==1.17.1
Requires-Dist: charset-normalizer==3.4.0
Requires-Dist: click==8.1.7
Requires-Dist: cryptography==43.0.3
Requires-Dist: distro==1.9.0
Requires-Dist: fastapi==0.115.4
Requires-Dist: h11==0.14.0
Requires-Dist: httpcore==1.0.6
Requires-Dist: httpx==0.27.2
Requires-Dist: idna==3.10
Requires-Dist: isodate==0.7.2
Requires-Dist: jiter==0.6.1
Requires-Dist: msal==1.31.0
Requires-Dist: msal-extensions==1.2.0
Requires-Dist: openai==1.52.2
Requires-Dist: portalocker==2.10.1
Requires-Dist: pycparser==2.22
Requires-Dist: pydantic==2.9.2
Requires-Dist: pydantic-core==2.23.4
Requires-Dist: PyJWT==2.9.0
Requires-Dist: python-dotenv==1.0.1
Requires-Dist: requests==2.32.3
Requires-Dist: six==1.16.0
Requires-Dist: sniffio==1.3.1
Requires-Dist: starlette==0.41.2
Requires-Dist: tqdm==4.66.6
Requires-Dist: typing-extensions==4.12.2
Requires-Dist: urllib3==2.2.3
Requires-Dist: uvicorn==0.32.0
